eoriver/__init__.py
eoriver/algorithms.py
eoriver/cli.py
eoriver-0.1.6.dist-info/METADATA
eoriver-0.1.6.dist-info/RECORD
eoriver-0.1.6.dist-info/WHEEL
eoriver-0.1.6.dist-info/entry_points.txt
eoriver-0.1.6.dist-info/top_level.txt
