Metadata-Version: 2.1
Name: eoriver
Version: 0.1.6
Summary: Earth Observation River Tools
Home-page: https://github.com/openearth/eo-river
Author: Gennadii Donchyts
Author-email: gennadiy.donchyts@gmail.com
License: MIT license
Keywords: eoriver
Platform: UNKNOWN
Classifier: Development Status :: 2 - Pre-Alpha
Classifier: Intended Audience :: Developers
Classifier: License :: OSI Approved :: MIT License
Classifier: Natural Language :: English
Classifier: Programming Language :: Python :: 2
Classifier: Programming Language :: Python :: 2.7
Classifier: Programming Language :: Python :: 3
Classifier: Programming Language :: Python :: 3.4
Classifier: Programming Language :: Python :: 3.5
Classifier: Programming Language :: Python :: 3.6
Requires-Dist: Click (>=6.0)
Requires-Dist: hydroengine (>=0.0.24)
Requires-Dist: geojson
